setup.py
coaaa.egg-info/PKG-INFO
coaaa.egg-info/SOURCES.txt
coaaa.egg-info/dependency_links.txt
coaaa.egg-info/top_level.txt
coaaa/lib/__init__.py
coaaa/lib/readexcel.py
coaaa/lib/writeexcel.py