Metadata-Version: 1.0
Name: coaaa
Version: 1.0.0
Summary: common
Home-page: UNKNOWN
Author: cxx
Author-email: cuixiaoxia@chinasofti.com
License: UNKNOWN
Platform: UNKNOWN
